cyber_connectors/MsSentinel.py
cyber_connectors/RestApi.py
cyber_connectors/Splunk.py
cyber_connectors/__init__.py
cyber_connectors/common.py
cyber_spark_data_connectors-0.0.7.dist-info/METADATA
cyber_spark_data_connectors-0.0.7.dist-info/WHEEL
cyber_spark_data_connectors-0.0.7.dist-info/licenses/LICENSE
cyber_spark_data_connectors-0.0.7.dist-info/RECORD
