Metadata-Version: 2.4
Name: cyber-spark-data-connectors
Version: 0.0.7
Summary: Cybersecurity-related custom data connectors for Spark (readers and writers).
License-Expression: Apache-2.0
License-File: LICENSE
Keywords: cybersecurity,apache spark,spark,splunk,log analytics,ms sentinel
Author: Alex Ott
Author-email: alexott@gmail.com
Requires-Python: >=3.9,<3.15
Classifier: Programming Language :: Python :: 3
Classifier: Programming Language :: Python :: 3.9
Classifier: Programming Language :: Python :: 3.10
Classifier: Programming Language :: Python :: 3.11
Classifier: Programming Language :: Python :: 3.12
Classifier: Programming Language :: Python :: 3.13
Classifier: Programming Language :: Python :: 3.14
Requires-Dist: azure-identity (>=1.25.1,<2.0.0)
Requires-Dist: azure-monitor-ingestion (>=1.1.0,<2.0.0)
Requires-Dist: azure-monitor-query (>=2.0.0,<3.0.0)
Requires-Dist: requests (>=2.32.5,<3.0.0)
Project-URL: Homepage, https://github.com/alexott/cyber-spark-data-connectors
Project-URL: Issues, https://github.com/alexott/cyber-spark-data-connectors/issues
